rpa_utils/__init__.py
rpa_utils/web.py
tests/__init__.py
tests/test_web.py
rpa_utils-1.0.1.dist-info/METADATA
rpa_utils-1.0.1.dist-info/WHEEL
rpa_utils-1.0.1.dist-info/top_level.txt
rpa_utils-1.0.1.dist-info/RECORD
